{
  "controller": {
    "restoreDirectoryPath": "./clustered-datastore-restore",
    "maxDataBrokerFutureCallbackQueueSize": 1000,
    "maxDataBrokerFutureCallbackPoolSize": 10,
    "metricCaptureEnabled": false,
    "mailboxCapacity": 1000,
    "moduleShardsConfig": "configuration/initial/module-shards.conf",
    "modulesConfig": "configuration/initial/modules.conf",
    "domNotificationRouterConfig": {
      "queueDepth": 65536,
      "spinTime": 0,
      "parkTime": 0,
      "unit": "MILLISECONDS"
    },
    "actorSystemConfig": {
      "akkaConfigPath": "singlenode/akka-default.conf",
      "factoryAkkaConfigPath": "singlenode/factory-akka-default.conf"
    },
    "schemaServiceConfig": {
      "topLevelModels": [
        { "nameSpace": "urn:opendaylight:inventory", "name": "opendaylight-inventory", "revision": "2013-08-19" },
        { "nameSpace": "urn:opendaylight:async-config:service", "name": "sal-async-config", "revision": "2017-06-19" },
        { "nameSpace": "urn:opendaylight:openflow:approved:extensions", "name": "openflow-approved-extensions", "revision": "2016-08-02" },
        { "nameSpace": "urn:opendaylight:openflow:augments", "name": "openflow-augments", "revision": "2015-02-25" },
        { "nameSpace": "urn:opendaylight:openflow:common:action", "name": "openflow-action", "revision": "2015-02-03" },
        { "nameSpace": "urn:opendaylight:openflow:common:instruction", "name": "openflow-instruction", "revision": "2013-07-31" },
        { "nameSpace": "urn:opendaylight:openflow:common:types", "name": "openflow-types", "revision": "2013-07-31" },
        { "nameSpace": "urn:opendaylight:openflow:config", "name": "openflow-configuration", "revision": "2014-06-30" },
        { "nameSpace": "urn:opendaylight:openflow:oxm", "name": "openflow-extensible-match", "revision": "2015-02-25" },
        { "nameSpace": "urn:opendaylight:openflow:protocol", "name": "openflow-protocol", "revision": "2013-07-31" },
        { "nameSpace": "urn:opendaylight:openflow:system", "name": "system-notifications", "revision": "2013-09-27" },
        { "nameSpace": "urn:opendaylight:action:types", "name": "opendaylight-action-types", "revision": "2013-11-12" },
        { "nameSpace": "urn:opendaylight:arbitrary:bitmask:fields", "name": "opendaylight-arbitrary-bitmask-fields", "revision": "2016-01-30" },
        { "nameSpace": "urn:opendaylight:group:types", "name": "opendaylight-group-types", "revision": "2013-10-18" },
        { "nameSpace": "urn:opendaylight:meter:types", "name": "opendaylight-meter-types", "revision": "2013-09-18" },
        { "nameSpace": "urn:opendaylight:model:match:types", "name": "opendaylight-match-types", "revision": "2013-10-26" },
        { "nameSpace": "urn:opendaylight:multipart:types", "name": "opendaylight-multipart-types", "revision": "2017-01-12" },
        { "nameSpace": "urn:opendaylight:opendaylight-ipv6-arbitrary-bitmask-fields", "name": "opendaylight-ipv6-arbitrary-bitmask-fields", "revision": "2016-02-24" },
        { "nameSpace": "urn:opendaylight:table:types", "name": "opendaylight-table-types", "revision": "2013-10-26" },
        { "nameSpace": "urn:opendaylight:echo:service", "name": "sal-echo", "revision": "2015-03-05" },
        { "nameSpace": "urn:opendaylight:flat-batch:service", "name": "sal-flat-batch", "revision": "2016-03-21" },
        { "nameSpace": "urn:opendaylight:flow:errors", "name": "flow-errors", "revision": "2013-11-16" },
        { "nameSpace": "urn:opendaylight:flow:inventory", "name": "flow-node-inventory", "revision": "2013-08-19" },
        { "nameSpace": "urn:opendaylight:flow:service", "name": "sal-flow", "revision": "2013-08-19" },
        { "nameSpace": "urn:opendaylight:flow:topology:discovery", "name": "flow-topology-discovery", "revision": "2013-08-19" },
        { "nameSpace": "urn:opendaylight:flow:transaction", "name": "flow-capable-transaction", "revision": "2015-03-04" },
        { "nameSpace": "urn:opendaylight:flows:service", "name": "sal-flows-batch", "revision": "2016-03-14" },
        { "nameSpace": "urn:opendaylight:group:service", "name": "sal-group", "revision": "2013-09-18" },
        { "nameSpace": "urn:opendaylight:groups:service", "name": "sal-groups-batch", "revision": "2016-03-15" },
        { "nameSpace": "urn:opendaylight:meter:service", "name": "sal-meter", "revision": "2013-09-18" },
        { "nameSpace": "urn:opendaylight:meters:service", "name": "sal-meters-batch", "revision": "2016-03-16" },
        { "nameSpace": "urn:opendaylight:module:config", "name": "node-config", "revision": "2014-10-15" },
        { "nameSpace": "urn:opendaylight:node:error:service", "name": "node-error", "revision": "2014-04-10" },
        { "nameSpace": "urn:opendaylight:packet:service", "name": "packet-processing", "revision": "2013-07-09" },
        { "nameSpace": "urn:opendaylight:port:service", "name": "sal-port", "revision": "2013-11-07" },
        { "nameSpace": "urn:opendaylight:queue:service", "name": "sal-queue", "revision": "2015-03-05" },
        { "nameSpace": "urn:opendaylight:role:service", "name": "sal-role", "revision": "2015-07-27" },
        { "nameSpace": "urn:opendaylight:service:barrier:common", "name": "barrier-common", "revision": "2016-03-15" },
        { "nameSpace": "urn:opendaylight:service:batch:common", "name": "batch-common", "revision": "2016-03-22" },
        { "nameSpace": "urn:opendaylight:table:service", "name": "sal-table", "revision": "2013-10-26" },
        { "nameSpace": "urn:opendaylight:direct:statistics", "name": "opendaylight-direct-statistics", "revision": "2016-05-11" },
        { "nameSpace": "urn:opendaylight:flow:statistics", "name": "opendaylight-flow-statistics", "revision": "2013-08-19" },
        { "nameSpace": "urn:opendaylight:flow:table:statistics", "name": "opendaylight-flow-table-statistics", "revision": "2013-12-15" },
        { "nameSpace": "urn:opendaylight:group:statistics", "name": "opendaylight-group-statistics", "revision": "2013-11-11" },
        { "nameSpace": "urn:opendaylight:meter:statistics", "name": "opendaylight-meter-statistics", "revision": "2013-11-11" },
        { "nameSpace": "urn:opendaylight:model:statistics:types", "name": "opendaylight-statistics-types", "revision": "2013-09-25" },
        { "nameSpace": "urn:opendaylight:port:statistics", "name": "opendaylight-port-statistics", "revision": "2013-12-14" },
        { "nameSpace": "urn:opendaylight:queue:statistics", "name": "opendaylight-queue-statistics", "revision": "2013-12-16" },
        { "nameSpace": "urn:opendaylight:params:xml:ns:yang:openflow:provider:config", "name": "openflow-provider-config", "revision": "2016-05-10" },
        { "nameSpace": "urn:opendaylight:params:xml:ns:yang:openflowplugin:rf:state", "name": "reconciliation-result-state", "revision": "2017-07-13" },
        { "nameSpace": "urn:opendaylight:params:xml:ns:yang:openflowplugin:sm:control", "name": "statistics-manager-control", "revision": "2015-08-12" },
        { "nameSpace": "urn:opendaylight:experimenter-message:service", "name": "sal-experimenter-message", "revision": "2015-10-20" },
        { "nameSpace": "urn:opendaylight:experimenter-mp-message:service", "name": "sal-experimenter-mp-message", "revision": "2015-10-20" },
        { "nameSpace": "urn:opendaylight:openflowplugin:experimenter:types", "name": "openflowplugin-experimenter-types", "revision": "2015-10-20" },
        { "nameSpace": "urn:opendaylight:openflowplugin:extension:general", "name": "openflowplugin-extension-general", "revision": "2014-07-14" },
        { "nameSpace": "urn:opendaylight:openflowplugin:extension:onf:bundle:service", "name": "sal-bundle", "revision": "2017-01-24" },
        { "nameSpace": "urn:opendaylight:openflowplugin:extension:onf", "name": "onf-extensions", "revision": "2017-01-24" },
        { "nameSpace": "urn:ietf:params:xml:ns:netconf:notification:1.0", "name": "notifications", "revision": "2008-07-14" },
        { "nameSpace": "urn:ietf:params:xml:ns:netmod:notification", "name": "nc-notifications", "revision": "2008-07-14" },
        { "nameSpace": "urn:ietf:params:xml:ns:yang:ietf-netconf-notifications", "name": "ietf-netconf-notifications", "revision": "2012-02-06" },
        { "nameSpace": "urn:opendaylight:params:xml:ns:yang:mdsal:core:general-entity", "name": "odl-general-entity", "revision": "2015-09-30" },
        { "nameSpace": "urn:opendaylight:params:xml:ns:yang:controller:md:sal:clustering:prefix-shard-configuration", "name": "prefix-shard-configuration", "revision": "2017-01-10" },
        { "nameSpace": "urn:opendaylight:params:xml:ns:yang:controller:config:distributed-datastore-provider", "name": "distributed-datastore-provider", "revision": "2014-06-12" },
        { "nameSpace": "urn:opendaylight:params:xml:ns:yang:controller:md:sal:clustering:entity-owners", "name": "entity-owners", "revision": "2015-08-04" },
        { "nameSpace": "urn:opendaylight:params:xml:ns:yang:openflowplugin:app:forwardingrules-manager:config", "name": "forwarding-rules-manager-config", "revision": "2016-05-11" },
        { "nameSpace": "urn:opendaylight:params:xml:ns:yang:openflowplugin:app:arbitrator-reconcile:service", "name": "arbitrator-reconcile", "revision": "2018-02-27" },
        { "nameSpace": "urn:opendaylight:serviceutils:upgrade", "name": "odl-serviceutils-upgrade", "revision": "2018-07-02" },
        { "nameSpace": "urn:opendaylight:params:xml:ns:yang:openflowplugin:app:frm-reconciliation:service", "name": "frm-reconciliation", "revision": "2018-02-27" },
        { "nameSpace": "urn:opendaylight:model:topology:inventory", "name": "opendaylight-topology-inventory", "revision": "2013-10-30" },
        { "nameSpace":"urn:ietf:params:xml:ns:yang:iana-if-type", "name":"iana-if-type","revision":"2017-01-19"},
        { "nameSpace":"urn:ietf:params:xml:ns:yang:ietf-interfaces", "name":"ietf-interfaces","revision":"2014-05-08"},
        { "nameSpace":"urn:ietf:params:xml:ns:yang:ietf-yang-types", "name":"ietf-yang-types","revision":"2013-07-15"},
        { "nameSpace":"urn:opendaylight:l2:types", "name":"opendaylight-l2-types","revision":"2013-08-27"},
        { "nameSpace":"urn:TBD:params:xml:ns:yang:network:ted", "name":"ted","revision":"2013-10-21"},
        { "nameSpace":"urn:TBD:params:xml:ns:yang:network-topology", "name":"network-topology","revision":"2013-10-21"},
        { "nameSpace":"urn:ietf:params:xml:ns:yang:ietf-inet-types", "name":"ietf-inet-types","revision":"2013-07-15"},
        { "nameSpace":"urn:opendaylight:yang:extension:yang-ext", "name":"yang-ext","revision":"2013-07-09"},
        { "nameSpace":"urn:opendaylight:params:xml:ns:yang:controller:config:distributed-datastore-provider", "name":"distributed-datastore-provider","revision":"2014-06-12"},
        { "nameSpace":"urn:opendaylight:params:xml:ns:yang:controller:md:sal:clustering:entity-owners", "name":"entity-owners","revision":"2015-08-04"},
        { "nameSpace":"urn:opendaylight:params:xml:ns:yang:controller:md:sal:clustering:prefix-shard-configuration", "name":"prefix-shard-configuration","revision":"2017-01-10"},
        { "nameSpace":"urn:opendaylight:params:xml:ns:yang:controller:md:sal:cluster:admin", "name":"cluster-admin","revision":"2015-10-13"},
        { "nameSpace":"urn:ietf:params:xml:ns:yang:ietf-yang-library", "name":"ietf-yang-library","revision":"2016-06-21"},
        { "nameSpace":"urn:ietf:params:xml:ns:yang:ietf-restconf", "name":"ietf-restconf","revision":"2017-01-26"},
        { "nameSpace":"urn:ietf:params:xml:ns:yang:ietf-restconf-monitoring", "name":"ietf-restconf-monitoring","revision":"2017-01-26"},
        { "nameSpace":"urn:opendaylight:params:xml:ns:yang:controller:md:sal:remote", "name": "sal-remote","revision":"2014-01-14"},
        { "nameSpace":"urn:sal:restconf:event:subscription", "name": "sal-remote-augment","revision":"2014-07-08"},
        { "nameSpace":"subscribe:to:notification", "name": "subscribe-to-notification","revision":"2016-10-28"}
      ]
    }
  },
  "restconf":{
    "inetAddress": "127.0.0.1",
    "httpPort":8888,
    "webSocketPort": 8185,
    "restconfServletContextPath":"/restconf",
    "jsonRestconfServiceType": "DRAFT_18"
  },
  "openflow": {
    "isStatisticsPollingOn": true,
    "barrierCountLimit": 25600,
    "barrierIntervalTimeoutLimit": 500,
    "basicTimerDelay": 3000,
    "echoReplyTimeout": 2000,
    "globalNotificationQuota": 64000,
    "maximumTimerDelay": 3679,
    "rpcRequestsQuota": 20000,
    "threadPoolMaxThreads": 32000,
    "threadPoolMinThreads": 1,
    "threadPoolTimeout": 60,
    "enableFlowRemovedNotification": true,
    "isStatisticsRpcEnabled": false,
    "skipTableFeatures": true,
    "switchFeaturesMandatory": false,
    "useSingleLayerSerialization": true,
    "frmDisableReconciliation": false,
    "frmStaleMarkingEnabled": false,
    "frmReconciliationRetryCount": 5,
    "frmBundleBasedReconciliationEnabled": false,
    "nonZeroUint32Type": 900000,
    "enableForwardingRulesManager": true,
    "deviceConnectionHoldTimeInSeconds": 0,
    "switchConfig": {
      "instanceName": "openflow-switch-connection-provider-default-impl",
      "port": 6653,
      "transportProtocol": 0,
      "useBarrier": true,
      "switchIdleTimeout": 15000,
      "keystore": "configuration/ssl/ctl.jks",
      "keystoreType": 0,
      "keystorePathType": 1,
      "keystorePassword": "opendaylight",
      "truststore": "configuration/ssl/truststore.jks",
      "truststoreType": 0,
      "truststorePathType": 1,
      "truststorePassword": "opendaylight",
      "certificatePassword": "opendaylight",
      "channelOutboundQueueSize": 1024
    }
  }
}